pydantic_type_chile_rut/__init__.py
pydantic_type_chile_rut/rut.py
pydantic_type_chile_rut-1.0.1.dist-info/METADATA
pydantic_type_chile_rut-1.0.1.dist-info/WHEEL
pydantic_type_chile_rut-1.0.1.dist-info/licenses/LICENSE
pydantic_type_chile_rut-1.0.1.dist-info/RECORD
