Metadata-Version: 2.4
Name: pydantic-type-chile-rut
Version: 1.0.1
Summary: Pydantic custom type for Chilean RUT validation and formatting
Project-URL: Homepage, https://github.com/yourusername/pydantic-type-chile-rut
Project-URL: Repository, https://github.com/yourusername/pydantic-type-chile-rut
Project-URL: Issues, https://github.com/yourusername/pydantic-type-chile-rut/issues
Author-email: Felipe Lolas <flolas@alumnos.uai.cl>
License-Expression: MIT
License-File: LICENSE
Keywords: chile,pydantic,rut,type,validation
Classifier: Development Status :: 4 - Beta
Classifier: Intended Audience :: Developers
Classifier: License :: OSI Approved :: MIT License
Classifier: Programming Language :: Python :: 3
Classifier: Programming Language :: Python :: 3.8
Classifier: Programming Language :: Python :: 3.9
Classifier: Programming Language :: Python :: 3.10
Classifier: Programming Language :: Python :: 3.11
Classifier: Programming Language :: Python :: 3.12
Classifier: Topic :: Software Development :: Libraries :: Python Modules
Classifier: Topic :: Utilities
Requires-Python: >=3.8
Requires-Dist: pydantic>=2.0.0
Provides-Extra: dev
Requires-Dist: build>=0.10.0; extra == 'dev'
Requires-Dist: mypy>=1.0.0; extra == 'dev'
Requires-Dist: pre-commit>=3.0.0; extra == 'dev'
Requires-Dist: pytest-cov>=4.0.0; extra == 'dev'
Requires-Dist: pytest>=7.0.0; extra == 'dev'
Requires-Dist: python-semantic-release>=8.0.0; extra == 'dev'
Requires-Dist: ruff>=0.1.0; extra == 'dev'
